sync/__init__.py
sync/application_exception.py
sync/dir_sync_command.py
sync/dir_sync_service.py
sync/file.py
sync/file_collection.py
sync/filesystem.py
sync/filesystem_factory.py
sync/main.py
sync/google_drive/__init__.py
sync/google_drive/google_drive_file.py
sync/google_drive/google_drive_filesystem.py
sync/google_drive/google_drive_filesystem_factory.py
sync/google_drive/google_drive_list_file_request.py
sync/google_drive/google_drive_list_file_response.py
sync/local/__init__.py
sync/local/local_file.py
sync/local/local_filesystem.py
sync/local/local_filesystem_factory.py
sync/local/local_list_file_response.py
sync/local/utils.py
dir_sync-0.2.0.dist-info/LICENSE.md
dir_sync-0.2.0.dist-info/METADATA
dir_sync-0.2.0.dist-info/WHEEL
dir_sync-0.2.0.dist-info/entry_points.txt
dir_sync-0.2.0.dist-info/top_level.txt
dir_sync-0.2.0.dist-info/RECORD
